{"current":{"color_text":"#3d4246","color_body_text":"#788188","color_sale_text":"#7796a8","color_borders":"#e8e9eb","color_button":"#7796a8","color_button_text":"#fff","color_small_button":"#fff","color_small_button_text":"#3d4246","color_text_field":"#fff","color_text_field_text":"#000","color_image_overlay_text":"#fff","color_image_overlay":"#3d4246","image_overlay_opacity":"0.25","color_body_bg":"#fff","type_header_family":"Google_Work+Sans_600_sans","type_header_base_size":"26px","type_base_family":"Google_Work+Sans_400_sans","type_base_size":"16px","type_bold_product_titles":false,"share_facebook":true,"share_twitter":true,"share_pinterest":true,"social_twitter_link":"","social_facebook_link":"","social_pinterest_link":"","social_instagram_link":"","social_tumblr_link":"","social_snapchat_link":"","social_youtube_link":"","social_vimeo_link":"","favicon":"shopify:\/\/shop_images\/favicon-32x32.png","checkout_header_image":"","checkout_logo_image":"","checkout_logo_position":"left","checkout_logo_size":"medium","checkout_body_background_image":"","checkout_body_background_color":"#fff","checkout_input_background_color_mode":"white","checkout_sidebar_background_image":"","checkout_sidebar_background_color":"#fafafa","checkout_heading_font":"Helvetica Neue","checkout_body_font":"Helvetica Neue","checkout_accent_color":"#1990c6","checkout_button_color":"#1990c6","checkout_error_color":"#ff6d6d","sections":{"header":{"type":"header","settings":{"align_logo":"left","logo":"shopify:\/\/shop_images\/Tillivery.png","logo_max_width":"100","main_linklist":"main-menu","message":false,"message_text":"$30 Off Your First Order • Limited Time Offer • Use Code TILLIVERY30 At Checkout","message_link":"shopify:\/\/pages\/signup","color_bg":"#8ec430","color_text":"#fff"}},"footer":{"type":"footer","settings":{"footer_linklist":"footer","footer_linklist_two":"","footer_newsletter_enable":false,"show_payment_icons":false}},"cart-template":{"type":"cart-template","settings":{"cart_notes_enable":false}},"product-template":{"type":"product-template","settings":{"image_size":"medium","show_quantity_selector":false,"show_variant_labels":true,"show_vendor":false,"enable_zoom":true,"show_share_buttons":true}},"collection-template":{"type":"collection-template","settings":{"layout":"grid","grid":"4","rows":"2","show_collection_image":true,"show_vendor":false,"sort_enable":true,"tags_enable":true}},"1492135790340":{"type":"logo-bar","blocks":{"1492135790340-0":{"type":"logo_image","settings":{"image":"shopify:\/\/shop_images\/Facebook-64.png","link":"https:\/\/www.facebook.com\/Tillivery\/"}},"1492135790340-1":{"type":"logo_image","settings":{"image":"shopify:\/\/shop_images\/instagram_new-512_2f869adb-9b88-45b1-af8b-0f7ad15ba888.png","link":"https:\/\/www.instagram.com\/tillivery\/"}},"1492136252338":{"type":"logo_image","settings":{"image":"shopify:\/\/shop_images\/email-2048-black.png","link":"mailto:info@tillivery.com"}}},"block_order":["1492135790340-0","1492135790340-1","1492136252338"],"settings":{"title":""}},"1492143466948":{"type":"hero","settings":{"image":"shopify:\/\/shop_images\/Pork-Green-Chili-Gnocci.jpg","alignment":"center","title":"PORK GREEN CHILI GNOCCHI","text":"<p>This TILL KITCHEN staple brings together authentic pork green chili with perfect pillows of house-made gnocchi. This richly flavored dish is 100% addictive!<\/p>","hero_size":"x-small","text_size":"medium","button_label":"THIS WEEK'S MENU","button_link":""}},"1492193994501":{"type":"slideshow","blocks":{"1492193994501-0":{"type":"image","settings":{"image":"shopify:\/\/shop_images\/salad_1322c750-76ac-446f-8065-e3fbd4077789.jpg","alignment":"top","title":"Our Kitchen. Your Table.","subheading":"Delicious chef-cooked meals, made with local & organic ingredients ... whenever possible","link":""}},"1492193994501-1":{"type":"image","settings":{"image":"shopify:\/\/shop_images\/delivery_a81a35af-29f4-48e3-9bda-7244391488f8.jpg","alignment":"top","title":"Come Home to Dinner - Done!","subheading":"Simply re-heat, relax & enjoy a freshly prepared meal with your family","link":""}},"1492885825825":{"type":"image","settings":{"image":"shopify:\/\/shop_images\/dinner.jpg","alignment":"top","title":"Affordable. Convenient. Smart.","subheading":"Our Family-style meals serve a family of 4 for as little as $49.99.","link":""}}},"block_order":["1492193994501-0","1492193994501-1","1492885825825"],"settings":{"autoplay":true,"autoplay_speed":"7000","slideshow_height":"small","text_size":"large"}},"1492197280919":{"type":"image-bar","blocks":{"1492197280919-0":{"type":"image","settings":{"image":"shopify:\/\/shop_images\/salad2.jpg","alignment":"center","link":"","cta_label":""}},"1492197280919-1":{"type":"image","settings":{"image":"shopify:\/\/shop_images\/soups.jpg","alignment":"center","link":"","cta_label":""}},"1492197280919-2":{"type":"image","settings":{"image":"shopify:\/\/shop_images\/entrees.jpg","alignment":"center","link":"","cta_label":""}}},"block_order":["1492197280919-0","1492197280919-1","1492197280919-2"],"settings":{"section_height":"small"}},"1492220927642":{"type":"custom-content","blocks":{"1492220936876":{"type":"html","settings":{"code":"<div style=\"background-color:#000;\"><\/div>","width":"100%"}}},"block_order":["1492220936876"],"settings":{"title":"Create delicious family meals with a few mouse-clicks!"}},"1492459732964":{"type":"custom-content","blocks":{"1494970310469":{"type":"html","settings":{"code":"<a href=\"\/pages\/signup\"> <div class=\"signup_button\"><\/div><\/a>","width":"100%"}}},"block_order":["1494970310469"],"settings":{"title":"Signup"}},"1493842120364":{"type":"custom-content","blocks":{"1493842128482":{"type":"html","settings":{"code":"<div id=\"shopify-section-1490051750765\" class=\"shopify-section index-section\">\n\n  <div class=\"grid grid--uniform grid--flush-bottom\">\n    \n      \n      <div class=\"grid__item medium-up--one-third text-center\">\n        \n          \n            <p>\n             <a href=\"\/pages\/menu\"> <img src=\"https:\/\/cdn.shopify.com\/s\/files\/1\/1837\/8723\/files\/select_480x480.png?v=1492893229\" alt=\"feature-row__image\"><\/a>\n            <\/p>\n          \n        \n        \n        \n          <div class=\"rte-setting\"><p>Create delicious family meals with a few mouse-clicks! Select to order Box style or A La Carte style.<br>\n<em>*minimum order $49.99\/week <\/em><\/p><\/div>\n        \n        \n      <\/div>\n    \n      \n      <div class=\"grid__item medium-up--one-third text-center\">\n        \n          \n            <p>\n            <a href=\"\/pages\/menu\">  <img src=\"https:\/\/cdn.shopify.com\/s\/files\/1\/1837\/8723\/files\/deliver-2_480x480.jpg?v=1492575025\" alt=\"feature-row__image\"><\/a>\n            <\/p>\n          \n        \n        \n        \n          <div class=\"rte-setting\"><p>Our Chef Team creates your meals, using local &amp; organic ingredients whenever possible. We deliver the freshly prepared goodness to your doorstep weekly.<br>\n<em>*4-delivery commitment <\/em><\/p><\/div>\n        \n        \n      <\/div>\n    \n      \n      <div class=\"grid__item medium-up--one-third text-center\">\n        \n          \n            <p>\n            <a href=\"\/pages\/menu\">  <img src=\"https:\/\/cdn.shopify.com\/s\/files\/1\/1837\/8723\/files\/savor_2030d317-1bcb-4213-afea-8af944ee03cb_480x480.png?v=1492898038\"><\/a>\n            <\/p>\n          \n        \n        \n        \n          <div class=\"rte-setting\"><p>Briefly heat your entrée &amp; soup. Dinner’s served! Gather loved ones around your table to celebrate delicious food, more time together &amp; fewer chores. <\/p><\/div>\n        \n        \n      <\/div>\n    \n  <\/div>\n\n  \n<\/div>","width":"100%"}}},"block_order":["1493842128482"],"settings":{"title":"Steps"}}},"content_for_index":["1492193994501","1492220927642","1492197280919","1492459732964","1493842120364","1492143466948","1492135790340"]},"presets":{"Default":{"color_text":"#3d4246","color_body_text":"#788188","color_sale_text":"#7796A8","color_borders":"#e8e9eb","color_button":"#7796A8","color_button_text":"#fff","color_small_button":"#fff","color_small_button_text":"#3d4246","color_text_field":"#fff","color_text_field_text":"#000","color_image_overlay_text":"#fff","color_image_overlay":"#3d4246","image_overlay_opacity":"0.25","color_body_bg":"#fff","type_header_family":"Google_Work+Sans_600_sans","type_header_base_size":"26px","type_base_family":"Google_Work+Sans_400_sans","type_base_size":"16px","type_bold_product_titles":false,"share_facebook":true,"share_twitter":true,"share_pinterest":true,"sections":{"header":{"type":"header","settings":{}},"hero":{"type":"hero","settings":{"text_size":"large"}},"slideshow":{"type":"slideshow","blocks":{"slideshow-0":{"type":"image","settings":{}},"slideshow-1":{"type":"image","settings":{}}},"block_order":["slideshow-0","slideshow-1"],"settings":{}},"featured-collections":{"type":"collection","settings":{"collection":"frontpage"}},"feature-row":{"type":"feature-row","settings":{}},"footer":{"type":"footer","settings":{"footer_linklist_two":""}}},"content_for_index":["hero","featured-collections","feature-row","slideshow"]}}}